rcplus_alloy_common/__init__.py
rcplus_alloy_common/cockpit.py
rcplus_alloy_common/constants.py
rcplus_alloy_common/custom_attributes.py
rcplus_alloy_common/encoder.py
rcplus_alloy_common/exceptions.py
rcplus_alloy_common/logging.py
rcplus_alloy_common/metrics.py
rcplus_alloy_common/multitenancy.py
rcplus_alloy_common/py.typed
rcplus_alloy_common/retry.py
rcplus_alloy_common/version.py
rcplus_alloy_common/airflow/__init__.py
rcplus_alloy_common/airflow/dag.py
rcplus_alloy_common/airflow/decorators.py
rcplus_alloy_common/airflow/hooks.py
rcplus_alloy_common/airflow/locking.py
rcplus_alloy_common/airflow/observability.py
rcplus_alloy_common/airflow/operators.py
rcplus_alloy_common/airflow/py.typed
rcplus_alloy_common/airflow/sensors.py
rcplus_alloy_common/airflow/utils.py
rcplus_alloy_common/aws/__init__.py
rcplus_alloy_common/aws/dynamodb.py
rcplus_alloy_common/aws/utils.py
rcplus_alloy_common/aws/wr.py
rcplus_alloy_common/aws/wr_utils.py
rcplus_alloy_common/gam/py.typed
rcplus_alloy_common/gam/vendor/README.md
rcplus_alloy_common/gam/vendor/__init__.py
rcplus_alloy_common/gam/vendor/audience_segments.py
rcplus_alloy_common/gam/vendor/common.py
rcplus_alloy_common/gam/vendor/companies.py
rcplus_alloy_common/gam/vendor/contacts.py
rcplus_alloy_common/gam/vendor/creatives.py
rcplus_alloy_common/gam/vendor/custom_targeting.py
rcplus_alloy_common/gam/vendor/forecast.py
rcplus_alloy_common/gam/vendor/inventory.py
rcplus_alloy_common/gam/vendor/labels.py
rcplus_alloy_common/gam/vendor/line_item_creative_associations.py
rcplus_alloy_common/gam/vendor/line_items.py
rcplus_alloy_common/gam/vendor/network.py
rcplus_alloy_common/gam/vendor/orders.py
rcplus_alloy_common/gam/vendor/placements.py
rcplus_alloy_common/gam/vendor/users.py
rcplus_alloy_common/xandr/py.typed
rcplus_alloy_common/xandr/vendor/README.md
rcplus_alloy_common/xandr/vendor/__init__.py
rcplus_alloy_common/xandr/vendor/batch_segment.py
rcplus_alloy_common/xandr/vendor/line_item.py
rcplus_alloy_common-8.9.3.dist-info/METADATA
rcplus_alloy_common-8.9.3.dist-info/WHEEL
rcplus_alloy_common-8.9.3.dist-info/licenses/LICENSE
rcplus_alloy_common-8.9.3.dist-info/RECORD
